Metadata-Version: 2.1
Name: carubi
Version: 1.1
Summary: carubi
Home-page: https://github.com/naistrai/carubi
Download-URL: https://github.com/naistrai/carubi/archive/v_01.tar.gz
Author: Nicetry
Author-email: admin@rizuki.my.id
License: MIT
Project-URL: Documentation, https://github.com/naistrai/carubi
Project-URL: Funding, https://donate.pypi.org
Project-URL: Say Thanks!, http://saythanks.io/to/example
Project-URL: Source, https://github.com/naistrai/carubi/
Project-URL: Tracker, https://github.com/naistrai/carubi/issues
Keywords: SOME,MEANINGFULL,KEYWORDS
Classifier: Development Status :: 3 - Alpha
Classifier: Intended Audience :: Developers
Classifier: Topic :: Software Development :: Build Tools
Classifier: License :: OSI Approved :: MIT License
Classifier: Programming Language :: Python :: 3
Classifier: Programming Language :: Python :: 3.4
Classifier: Programming Language :: Python :: 3.5
Classifier: Programming Language :: Python :: 3.6
License-File: LICENSE
Requires-Dist: validators
Requires-Dist: beautifulsoup4
Requires-Dist: discorudo
Requires-Dist: discordautochat
